{
  "image": [
    "图4：中芯国际归母净利润情况概览",
    "图5：中芯国际营业收入及增速趋势",
    "图6：中芯国际毛利率和净利率变化",
    "图7：中芯国际季度归母净利润及增速",
    "图8：中芯国际25Q1下游应用领域结构",
    "图9：中芯国际全球部署示意图",
    "图10：中芯国际工艺迭代升级进展",
    "图11：中芯国际产能利用率变化",
    "图12：中芯国际不同地域营收分布",
    "图13：中芯国际研发投入趋势",
    "图14：中芯国际资本开支计划",
    "图15：中芯国际客户基础分布",
    "中芯国际净利润图表",
    "中芯国际营收增长趋势图",
    "中芯国际毛利率变化图表",
    "中芯国际季度业绩图表",
    "中芯国际下游应用分布图",
    "中芯国际全球布局图",
    "中芯国际技术工艺图",
    "中芯国际产能利用图表",
    "中芯国际地域营收图",
    "中芯国际研发投入图",
    "中芯国际投资计划图",
    "中芯国际客户结构图",
    "芯片制造良率数据图表",
    "半导体行业分析图表",
    "晶圆代工工艺流程图表",
    "集成电路制造图表",
    "芯片设计流程图",
    "半导体材料图表",
    "芯片测试图表",
    "芯片封装图表",
    "芯片质量分析图表",
    "芯片成本结构图表",
    "芯片市场分析图表",
    "芯片技术路线图",
    "芯片应用场景图",
    "芯片供应链图表",
    "芯片竞争格局图",
    "芯片发展趋势图",
    "芯片投资分析图",
    "芯片风险评估图",
    "芯片政策环境图",
    "芯片人才结构图",
    "芯片研发投入图",
    "芯片专利申请图",
    "芯片标准制定图",
    "芯片国际合作图",
    "芯片本土化图表",
    "芯片安全可控图",
    "芯片绿色发展图",
    "芯片数字化转型图",
    "芯片智能化图表",
    "芯片网络化图表",
    "芯片生态建设图"
  ],
  "text": [
    "中芯国际的主要业务和核心技术是什么？",
    "中芯国际在晶圆代工行业的市场地位如何？",
    "中芯国际从2000年到2020年的发展历程中有哪些重要节点？",
    "中芯国际面临的主要风险和挑战有哪些？",
    "中芯国际的技术工艺水平和制程能力如何？",
    "中芯国际的供应链和合作伙伴关系如何？",
    "中芯国际的未来发展前景和增长潜力如何？",
    "中芯国际的研发投入和专利申请情况如何？",
    "中芯国际的客户基础和市场分布如何？",
    "中芯国际的产能利用率显著提升体现在哪些方面？"
  ],
  "table": [
    "中芯国际的营业收入从2024年开始的变化趋势如何？",
    "中芯国际的毛利率和净利率变化趋势如何？",
    "中芯国际在不同地域的营收分布情况如何？",
    "中芯国际的季度归母净利润及增速情况如何？",
    "中芯国际25Q1下游应用领域结构情况如何？",
    "中芯国际的资本开支和投资计划如何？",
    "中芯国际的工艺迭代升级进展如何？",
    "中芯国际的研发投入和专利申请情况如何？"
  ],
  "hybrid": [
    "中芯国际的整体财务表现和业务发展情况如何？",
    "中芯国际的技术实力、市场地位和未来前景如何？",
    "中芯国际的营收、利润、研发投入等关键指标分析",
    "中芯国际的全球布局、客户结构和竞争优势分析",
    "中芯国际的工艺升级、产能扩张和投资计划分析",
    "中芯国际的风险挑战、发展机遇和增长潜力分析"
  ],
  "smart": [
    "请分析中芯国际的整体情况",
    "中芯国际有哪些关键优势？",
    "请总结中芯国际的发展前景",
    "中芯国际面临哪些挑战？",
    "请综合分析中芯国际的财务状况",
    "中芯国际的核心竞争力是什么？",
    "请评估中芯国际的投资价值",
    "中芯国际的未来发展方向是什么？"
  ]
}
